blackjack/__init__.py
blackjack/app.py
blackjack/type.py
blackjack/card_png/10_of_clubs.png
blackjack/card_png/10_of_diamonds.png
blackjack/card_png/10_of_hearts.png
blackjack/card_png/10_of_spades.png
blackjack/card_png/2_of_clubs.png
blackjack/card_png/2_of_diamonds.png
blackjack/card_png/2_of_hearts.png
blackjack/card_png/2_of_spades.png
blackjack/card_png/3_of_clubs.png
blackjack/card_png/3_of_diamonds.png
blackjack/card_png/3_of_hearts.png
blackjack/card_png/3_of_spades.png
blackjack/card_png/4_of_clubs.png
blackjack/card_png/4_of_diamonds.png
blackjack/card_png/4_of_hearts.png
blackjack/card_png/4_of_spades.png
blackjack/card_png/5_of_clubs.png
blackjack/card_png/5_of_diamonds.png
blackjack/card_png/5_of_hearts.png
blackjack/card_png/5_of_spades.png
blackjack/card_png/6_of_clubs.png
blackjack/card_png/6_of_diamonds.png
blackjack/card_png/6_of_hearts.png
blackjack/card_png/6_of_spades.png
blackjack/card_png/7_of_clubs.png
blackjack/card_png/7_of_diamonds.png
blackjack/card_png/7_of_hearts.png
blackjack/card_png/7_of_spades.png
blackjack/card_png/8_of_clubs.png
blackjack/card_png/8_of_diamonds.png
blackjack/card_png/8_of_hearts.png
blackjack/card_png/8_of_spades.png
blackjack/card_png/9_of_clubs.png
blackjack/card_png/9_of_diamonds.png
blackjack/card_png/9_of_hearts.png
blackjack/card_png/9_of_spades.png
blackjack/card_png/ace_of_clubs.png
blackjack/card_png/ace_of_diamonds.png
blackjack/card_png/ace_of_hearts.png
blackjack/card_png/ace_of_spades.png
blackjack/card_png/back.png
blackjack/card_png/back@2x.png
blackjack/card_png/black_joker.png
blackjack/card_png/jack_of_clubs.png
blackjack/card_png/jack_of_diamonds.png
blackjack/card_png/jack_of_hearts.png
blackjack/card_png/jack_of_spades.png
blackjack/card_png/king_of_clubs.png
blackjack/card_png/king_of_diamonds.png
blackjack/card_png/king_of_hearts.png
blackjack/card_png/king_of_spades.png
blackjack/card_png/queen_of_clubs.png
blackjack/card_png/queen_of_diamonds.png
blackjack/card_png/queen_of_hearts.png
blackjack_amiyuki7-0.1.dist-info/LICENSE
blackjack_amiyuki7-0.1.dist-info/WHEEL
blackjack_amiyuki7-0.1.dist-info/METADATA
blackjack_amiyuki7-0.1.dist-info/RECORD
