Metadata-Version: 2.1
Name: blackjack-amiyuki7
Version: 0.1
Summary: Blackjack made with pygame
Author-email: Alexander Xie <amiyuki788@gmail.com>
Requires-Python: >=3.10
Classifier: License :: OSI Approved :: MIT License
Requires-Dist: pygame>=2.5.1
Project-URL: Home, https://github.com/amiyuki7/blackjack
